plotaris/__init__.py
plotaris/core/__init__.py
plotaris/core/axes.py
plotaris/core/axisgrid.py
plotaris/core/chart.py
plotaris/core/facet.py
plotaris/core/group.py
plotaris/core/label.py
plotaris/core/palette.py
plotaris/marks/__init__.py
plotaris/marks/bar.py
plotaris/marks/base.py
plotaris/marks/line.py
plotaris/marks/point.py
plotaris/py.typed
plotaris/utils.py
plotaris-0.1.3.dist-info/WHEEL
plotaris-0.1.3.dist-info/METADATA
plotaris-0.1.3.dist-info/RECORD
