Metadata-Version: 2.3
Name: plotaris
Version: 0.1.3
Summary: 
Keywords: 
Author: daizutabi
Author-email: daizutabi <daizutabi@gmail.com>
License: MIT License
Classifier: Development Status :: 4 - Beta
Classifier: Programming Language :: Python
Classifier: Programming Language :: Python :: 3.12
Classifier: Programming Language :: Python :: 3.13
Classifier: Programming Language :: Python :: 3.14
Requires-Dist: matplotlib>=3.10
Requires-Dist: polars>=1.0.0
Requires-Python: >=3.12
Project-URL: Documentation, https://github.com/daizutabi/plotaris
Project-URL: Source, https://github.com/daizutabi/plotaris
Project-URL: Issues, https://github.com/daizutabi/plotaris/issues
